LICENSE.txt
MANIFEST.in
setup.py
vaex/distributed/__init__.py
vaex/distributed/__main__.py
vaex/distributed/_version.py
vaex_distributed.egg-info/PKG-INFO
vaex_distributed.egg-info/SOURCES.txt
vaex_distributed.egg-info/dependency_links.txt
vaex_distributed.egg-info/not-zip-safe
vaex_distributed.egg-info/requires.txt
vaex_distributed.egg-info/top_level.txt