Metadata-Version: 1.0
Name: vaex-distributed
Version: 0.3.0
Summary: Distributed dataset for vaex
Home-page: https://www.github.com/maartenbreddels/vaex
Author: Maarten A. Breddels
Author-email: maartenbreddels@gmail.com
License: MIT
Platform: UNKNOWN
